vtk_lookingglass-1.0.0.data/data/include/vtkrenderinglookingglass-0.1/vtkLookingGlassInterface.h
vtk_lookingglass-1.0.0.data/data/include/vtkrenderinglookingglass-0.1/vtkLookingGlassPass.h
vtk_lookingglass-1.0.0.data/data/include/vtkrenderinglookingglass-0.1/vtkRenderingLookingGlassModule.h
vtk_lookingglass-1.0.0.data/data/include/vtkrenderinglookingglass-0.1/vtkXLookingGlassRenderWindow.h
vtk_lookingglass-1.0.0.data/data/lib/cmake/vtk/vtkRenderingLookingGlass-targets-release.cmake
vtk_lookingglass-1.0.0.data/data/lib/cmake/vtk/vtkRenderingLookingGlass-targets.cmake
vtk_lookingglass-1.0.0.data/data/lib/cmake/vtk/vtkRenderingLookingGlass-vtk-module-find-packages.cmake
vtk_lookingglass-1.0.0.data/data/lib/cmake/vtk/vtkRenderingLookingGlass-vtk-module-properties.cmake
vtk_lookingglass-1.0.0.data/data/lib/cmake/vtk/vtkmodules-vtk-python-module-properties.cmake
vtk_lookingglass-1.0.0.data/data/lib/vtk/hierarchy/vtkRenderingLookingGlass/vtkRenderingLookingGlass-hierarchy.txt
vtk_lookingglass-1.0.0.data/data/lib/vtk/vtkRenderingLookingGlass/LICENSE
vtkmodules/libHoloPlayCore.so
vtkmodules/libvtkRenderingLookingGlass.so
vtkmodules/libvtkRenderingLookingGlass.so.0.1.0
vtkmodules/libvtkRenderingLookingGlass.so.1
vtkmodules/vtkRenderingLookingGlass.cpython-39-x86_64-linux-gnu.so
vtk_lookingglass-1.0.0.dist-info/LICENSE
vtk_lookingglass-1.0.0.dist-info/METADATA
vtk_lookingglass-1.0.0.dist-info/WHEEL
vtk_lookingglass-1.0.0.dist-info/top_level.txt
vtk_lookingglass-1.0.0.dist-info/RECORD
